pycov3/App.py
pycov3/Directory.py
pycov3/File.py
pycov3/Sequence.py
pycov3/__init__.py
pycov3/cli.py
pycov3-2.1.0.dist-info/LICENSE
pycov3-2.1.0.dist-info/METADATA
pycov3-2.1.0.dist-info/WHEEL
pycov3-2.1.0.dist-info/entry_points.txt
pycov3-2.1.0.dist-info/top_level.txt
pycov3-2.1.0.dist-info/RECORD
