Metadata-Version: 2.1
Name: pycov3
Version: 2.1.0
Summary: Generate cov3 files used in DEMIC
Author-email: Charlie Bushman <ctbushman@gmail.com>
Maintainer-email: Charlie Bushman <ctbushman@gmail.com>
Project-URL: Homepage, https://github.com/Ulthran/pycov3/
Project-URL: Bug Reports, https://github.com/Ulthran/pycov3/issues
Project-URL: Source, https://github.com/Ulthran/pycov3/
Classifier: Development Status :: 5 - Production/Stable
Classifier: License :: OSI Approved :: MIT License
Classifier: Programming Language :: Python :: 3
Classifier: Programming Language :: Python :: 3.7
Classifier: Programming Language :: Python :: 3.8
Classifier: Programming Language :: Python :: 3.9
Classifier: Programming Language :: Python :: 3.10
Classifier: Programming Language :: Python :: 3.11
Classifier: Programming Language :: Python :: 3 :: Only
Requires-Python: >=3.7
License-File: LICENSE
Provides-Extra: dev
Requires-Dist: black ; extra == 'dev'
Provides-Extra: test
Requires-Dist: pytest ; extra == 'test'
Requires-Dist: pytest-cov ; extra == 'test'
